LICENSE
freshpaper.py
freshpaper-1.2.2.dist-info/entry_points.txt
freshpaper-1.2.2.dist-info/LICENSE
freshpaper-1.2.2.dist-info/WHEEL
freshpaper-1.2.2.dist-info/METADATA
freshpaper-1.2.2.dist-info/RECORD
