Metadata-Version: 2.1
Name: freshpaper
Version: 1.2.2
Summary: Program to automatically set Bing's `Photo of the day` as your Desktop's wallpaper.
Home-page: https://github.com/guptarohit/freshpaper
License: BSD-3-Clause
Keywords: wallpaper changer,wallpaper,bing,bing wallpaper,nasa-apod
Author: Rohit Gupta
Author-email: rohitgtech+git@gmail.com
Requires-Python: >=3.6,<4.0
Classifier: Development Status :: 5 - Production/Stable
Classifier: License :: OSI Approved :: BSD License
Classifier: Operating System :: MacOS
Classifier: Operating System :: Microsoft :: Windows
Classifier: Operating System :: POSIX :: Linux
Classifier: Programming Language :: Python :: 3
Classifier: Programming Language :: Python :: 3.10
Classifier: Programming Language :: Python :: 3.6
Classifier: Programming Language :: Python :: 3.7
Classifier: Programming Language :: Python :: 3.8
Classifier: Programming Language :: Python :: 3.9
Classifier: Topic :: Utilities
Requires-Dist: click
Requires-Dist: pillow (>=7.0,<8.0)
Project-URL: Repository, https://github.com/guptarohit/freshpaper
